{
  "taglib-imports": [
    "./load-more/marko.json"
  ],
  "<bulletin-latest-content-feed-block>": {
    "template": "./latest-content-feed.marko",
    "<query-params>": {},
    "<flow>": {},
    "@section-id": {
      "type": "number",
      "required": true
    }
  },
  "<bulletin-latest-content-card-deck-block>": {
    "template": "./latest-content-card-deck.marko",
    "<query-params>": {},
    "<flow>": {},
    "@section-id": {
      "type": "number",
      "required": true
    }
  },
  "<bulletin-follow-us-block>": {
    "template": "./follow-us.marko"
  },
  "<bulletin-most-recent-block>": {
    "template": "./most-recent.marko"
  },
  "<bulletin-magazine-publications-block>": {
    "template": "./magazine-publications.marko",
    "<publication-params>": {}
  },
  "<bulletin-related-content-block>": {
    "template": "./related-content.marko",
    "@content-id": "number"
  },
  "<bulletin-latest-in-section-block>": {
    "template": "./latest-in-section.marko",
    "<content>": {
      "@id": "number"
    },
    "<section>": {
      "@id": "number",
      "@name": "string"
    }
  },
  "<bulletin-site-footer>": {
    "template": "./site-footer.marko"
  },
  "<bulletin-leaderboard-block>": {
    "template": "./leaderboard.marko"
  },
  "<bulletin-announcements-block>": {
    "template": "./announcements.marko"
  },
  "<bulletin-message-block>": {
    "template": "./message.marko"
  },
  "<bulletin-content-hero-card-block>": {
    "template": "./content-hero-card.marko"
  },
  "<bulletin-content-featured-block>": {
    "template": "./content-featured.marko"
  },
  "<bulletin-section-list-block>": {
    "template": "./section-list.marko",
    "<list>": {}
  },
  "<bulletin-standard-section-list-block>": {
    "template": "./standard-section-list.marko",
    "<list>": {}
  },
  "<bulletin-watch-listen-block>": {
    "template": "./watch-listen.marko"
  },
  "<bulletin-exhibits-mr-block>": {
    "template": "./exhibits-mr.marko"
  },
  "<bulletin-eposters-mr-block>": {
    "template": "./eposters-mr.marko"
  },
  "<bulletin-exhibitors-banner-block>": {
    "template": "./exhibitors-banner.marko"
  },
  "<bulletin-early-career-block>": {
    "template": "./early-career.marko"
  },
  "<bulletin-event-schedule-block>": {
    "template": "./event-schedule.marko"
  },
  "<bulletin-featured-exhibitors-full-block>": {
    "template": "./featured-exhibitors-full.marko"
  },
  "<bulletin-company-content-list-block>": {
    "template": "./company-content-list.marko"
  },
  "<bulletin-company-header-block>": {
    "template": "./company-header.marko"
  },
  "<bulletin-featured-exhibitors-block>": {
    "template": "./featured-exhibitors.marko"
  },
  "<bulletin-content-hero-block>": {
    "template": "./content-hero.marko"
  },
  "<bulletin-hero-block>": {
    "template": "./hero.marko"
  },
  "<bulletin-standard-hero-block>": {
    "template": "./standard-hero.marko"
  },
  "<bulletin-qcor-chat-button-block>": {
    "template": "./qcor-chat-button.marko"
  },
  "<bulletin-qcor-early-career-plenary-buttons-block>": {
    "template": "./qcor-early-career-plenary-buttons.marko"
  },
  "<bulletin-global-right-rail-block>": {
    "template": "./global-right-rail.marko"
  },
  "<bulletin-science-news-block>": {
    "template": "./science-news.marko"
  }
}
